{
  "project_info": {
    "project_number": "822558183576",
    "firebase_url": "https://hendev-54e8b.firebaseio.com",
    "project_id": "hendev-54e8b",
    "storage_bucket": "hendev-54e8b.appspot.com"
  },
  "client": [
    {
      "client_info": {
        "mobilesdk_app_id": "1:822558183576:android:a223791749782da61f80ed",
        "android_client_info": {
          "package_name": "com.hendev.firebaseproject"
        }
      },
      "oauth_client": [
        {
          "client_id": "822558183576-u459ua330gdkpi9vrt6e2cf82a24pckc.apps.googleusercontent.com",
          "client_type": 3
        }
      ],
      "api_key": [
        {
          "current_key": "AIzaSyAPWwtmMux3o0MR8dsXM6wRyy-4mKqXTK8"
        }
      ],
      "services": {
        "appinvite_service": {
          "other_platform_oauth_client": [
            {
              "client_id": "822558183576-u459ua330gdkpi9vrt6e2cf82a24pckc.apps.googleusercontent.com",
              "client_type": 3
            }
          ]
        }
      }
    },
    {
      "client_info": {
        "mobilesdk_app_id": "1:822558183576:android:6e395dff1799f3b31f80ed",
        "android_client_info": {
          "package_name": "com.hendev.instahen"
        }
      },
      "oauth_client": [
        {
          "client_id": "822558183576-u459ua330gdkpi9vrt6e2cf82a24pckc.apps.googleusercontent.com",
          "client_type": 3
        }
      ],
      "api_key": [
        {
          "current_key": "AIzaSyAPWwtmMux3o0MR8dsXM6wRyy-4mKqXTK8"
        }
      ],
      "services": {
        "appinvite_service": {
          "other_platform_oauth_client": [
            {
              "client_id": "822558183576-u459ua330gdkpi9vrt6e2cf82a24pckc.apps.googleusercontent.com",
              "client_type": 3
            }
          ]
        }
      }
    }
  ],
  "configuration_version": "1"
}